[
  {
    "id": "pgi.movie.a",
    "image_id": "pgi.movie.a",
    "construction_image_id": "generic.construction.2",
    "name": {
      "DE": "Kino",
      "EN": "Movie Theater",
      "ES": "Cine",
      "FR": "Cinéma",
      "IT": "Cinema",
      "PT": "Cinema"
    },
    "seal": "pgi",
    "zone": "COMMERCIAL",
    "category": "COMMERCE",
    "industry_type": "MOVIE",
    "required_inventions": [],
    "commerce": {}
  },
  {
    "id": "pgi.movie.b",
    "image_id": "pgi.movie.b",
    "construction_image_id": "generic.construction.2",
    "name": {
      "DE": "Kino",
      "EN": "Movie Theater",
      "ES": "Cine",
      "FR": "Cinéma",
      "IT": "Cinema",
      "PT": "Cinema"
    },
    "seal": "pgi",
    "zone": "COMMERCIAL",
    "category": "COMMERCE",
    "industry_type": "MOVIE",
    "required_inventions": [],
    "commerce": {}
  }
]